maspy/__init__.py
maspy/admin.py
maspy/agent.py
maspy/communication.py
maspy/environment.py
maspy/error.py
maspy/logger.py
maspy/logger_config.json
maspy/py.typed
maspy/utils.py
maspy/learning/__init__.py
maspy/learning/core.py
maspy/learning/ml_utils.py
maspy/learning/modelling.py
maspy/learning/py.typed
maspy/learning/space.py
maspy_ml-2025.11.9.dist-info/METADATA
maspy_ml-2025.11.9.dist-info/WHEEL
maspy_ml-2025.11.9.dist-info/top_level.txt
maspy_ml-2025.11.9.dist-info/RECORD
