Metadata-Version: 2.4
Name: maspy-ml
Version: 2025.11.9
Summary: Multi-Agent System for Python (MASPY) with Machine Learning proprieties
Author: Alexandre Mellado
Author-email: <melladoallm@gmail.com>
Keywords: python,autonomous agents,multi-agent system,machine learning
Classifier: Development Status :: 5 - Production/Stable
Classifier: Intended Audience :: Developers
Classifier: Programming Language :: Python :: 3.12
Classifier: Operating System :: Unix
Classifier: Operating System :: Microsoft :: Windows
Requires-Dist: numpy
Requires-Dist: pandas
Requires-Dist: openpyxl
Dynamic: author
Dynamic: author-email
Dynamic: classifier
Dynamic: description
Dynamic: description-content-type
Dynamic: keywords
Dynamic: requires-dist
Dynamic: summary
